amof/__init__.py
amof/atom.py
amof/bad.py
amof/cn.py
amof/msd.py
amof/plot.py
amof/rdf.py
amof/structure.py
amof/symbols.py
amof/trajectory.py
amof/coordination/__init__.py
amof/coordination/buildingunits.py
amof/coordination/core.py
amof/coordination/reduce.py
amof/coordination/zif.py
amof/elastic/__init__.py
amof/elastic/core.py
amof/elastic/elate.py
amof/files/__init__.py
amof/files/cp2k.py
amof/files/lammps.py
amof/files/molsys.py
amof/files/operation.py
amof/files/path.py
amof/pore/__init__.py
amof/pore/core.py
amof/pore/pysimmzeopp.py
amof/ring/__init__.py
amof/ring/core.py
amof/ring/template/input.inp
amof/ring/template/options
amof/tests/__init__.py
amof-1.1.0.dist-info/METADATA
amof-1.1.0.dist-info/WHEEL
amof-1.1.0.dist-info/licenses/LICENSE.txt
amof-1.1.0.dist-info/RECORD
