Metadata-Version: 2.1
Name: amof
Version: 1.1.0
Summary: A python package to analyze Molecular Dynamics (MD) trajectories of amorphous Metal-Organic Frameworks (MOFs). 
Project-URL: Documentation, https://github.com/casteln/amof#readme
Project-URL: Issues, https://github.com/casteln/amof/issues
Project-URL: Source, https://github.com/casteln/amof
Author-email: Nicolas Castel <nicolas.castel@chimieparistech.psl.eu>
License-Expression: MIT
License-File: LICENSE.txt
Classifier: Development Status :: 4 - Beta
Classifier: Programming Language :: Python
Classifier: Programming Language :: Python :: 3.7
Classifier: Programming Language :: Python :: 3.8
Classifier: Programming Language :: Python :: 3.9
Classifier: Programming Language :: Python :: 3.10
Classifier: Programming Language :: Python :: 3.11
Classifier: Programming Language :: Python :: Implementation :: CPython
Classifier: Programming Language :: Python :: Implementation :: PyPy
Requires-Python: >=3.7
Requires-Dist: ase~=3.20.1
Requires-Dist: atomman
Requires-Dist: joblib
Requires-Dist: matplotlib
Requires-Dist: networkx
Requires-Dist: numpy
Requires-Dist: pandas
Requires-Dist: pymatgen
Requires-Dist: requests
Requires-Dist: scipy
Requires-Dist: xarray~=0.19.0
Provides-Extra: graphics
Requires-Dist: bokeh; extra == 'graphics'
Requires-Dist: cairosvg; extra == 'graphics'
Requires-Dist: holoviews; extra == 'graphics'
Requires-Dist: hvplot; extra == 'graphics'
Requires-Dist: selenium; extra == 'graphics'
Provides-Extra: rdf
Requires-Dist: asap3; extra == 'rdf'
